rmfit/__init__.py
rmfit/convective_blueshift.py
rmfit/likelihood.py
rmfit/mcmc_help.py
rmfit/priors.py
rmfit/rmfit.py
rmfit/stats_help.py
rmfit/utils.py
rmfit-1.0.2.dist-info/LICENSE
rmfit-1.0.2.dist-info/METADATA
rmfit-1.0.2.dist-info/WHEEL
rmfit-1.0.2.dist-info/top_level.txt
rmfit-1.0.2.dist-info/RECORD
