Metadata-Version: 2.1
Name: rmfit
Version: 1.0.2
Summary: Fit Rossiter McLaughlin Data
Home-page: https://github.com/gummiks/rmfit/
Author: Gudmundur Stefansson
Author-email: gummiks@gmail.com
License: GPLv3
Keywords: Astronomy
Classifier: Topic :: Scientific/Engineering :: Astronomy
License-File: LICENSE
Requires-Dist: emcee
Requires-Dist: batman-package
Requires-Dist: radvel
Requires-Dist: corner
Requires-Dist: pandas
Requires-Dist: h5py
Requires-Dist: pytransit
